odoo/addons/project_task_restrict_stage_timesheets/README.rst
odoo/addons/project_task_restrict_stage_timesheets/__init__.py
odoo/addons/project_task_restrict_stage_timesheets/__manifest__.py
odoo/addons/project_task_restrict_stage_timesheets/i18n/es.po
odoo/addons/project_task_restrict_stage_timesheets/models/__init__.py
odoo/addons/project_task_restrict_stage_timesheets/models/account_analytic_line.py
odoo/addons/project_task_restrict_stage_timesheets/models/project_task_type.py
odoo/addons/project_task_restrict_stage_timesheets/readme/CONFIGURE.rst
odoo/addons/project_task_restrict_stage_timesheets/readme/CONTRIBUTORS.rst
odoo/addons/project_task_restrict_stage_timesheets/readme/DESCRIPTION.rst
odoo/addons/project_task_restrict_stage_timesheets/readme/USAGE.rst
odoo/addons/project_task_restrict_stage_timesheets/security/project_task_restrict_stage_timesheets_security.xml
odoo/addons/project_task_restrict_stage_timesheets/static/description/icon.png
odoo/addons/project_task_restrict_stage_timesheets/static/description/index.html
odoo/addons/project_task_restrict_stage_timesheets/tests/__init__.py
odoo/addons/project_task_restrict_stage_timesheets/tests/test_project_task_restrict_stage_timesheets.py
odoo/addons/project_task_restrict_stage_timesheets/views/project_task_type_views.xml
odoo_addon_project_task_restrict_stage_timesheets-16.0.1.0.0.1.dist-info/METADATA
odoo_addon_project_task_restrict_stage_timesheets-16.0.1.0.0.1.dist-info/WHEEL
odoo_addon_project_task_restrict_stage_timesheets-16.0.1.0.0.1.dist-info/top_level.txt
odoo_addon_project_task_restrict_stage_timesheets-16.0.1.0.0.1.dist-info/RECORD
